[
    {
        "text": "Disculpa, soy estúpida. Tal vez escribiste mal el comando y no te entiendo",
        "imageUrl": "https://i.imgur.com/e4uM3z6.jpg"
    },
    {
        "text": "No entiendo, ¿quieres usar un comando? Quieres usar uno, ¿verdad?, ¿prueba revisar cómo lo escribes?'",
        "imageUrl": "https://i.imgur.com/uuLuxtj.jpg"
    },
    {
        "text": "La verdad, no tengo ni idea de qué pueda ser **\"{commandName}\"**, ¿seguro que lo escribiste bien? Recuerda que soy un bot, eh",
        "imageUrl": "https://i.imgur.com/AHdc7E2.jpg"
    },
    {
        "text": "Busqué en todo el manual y no encontré el comando que me pediste. Perdóname, PERDÓNAME WAAAAAAAAH",
        "imageUrl": "https://i.imgur.com/wOxRi72.jpg"
    },
    {
        "text": "No logré encontrar tu comando en mi librito. ¿Lo habrás escrito mal?",
        "imageUrl": "https://i.imgur.com/avTSSa4.jpg"
    },
    {
        "text": "Te juro que no encuentro ningún comando así, perdón 🥺",
        "imageUrl": "https://i.imgur.com/gqTzYJA.jpg"
    }
]